pyernluefter/__init__.py
pyernluefter/convert.py
pyernluefter/tests/__init__.py
pyernluefter/tests/test_web.py
pyernluefter/tests/test_structure/?export=1
pyernluefter/tests/test_structure/__init__.py
pyernluefter/tests/test_structure/bayernluefter_mock_server.py
pyernluefter/tests/test_structure/export.txt
pyernluefter/tests/test_structure/server_control.py
pyernluefter/tests/test_structure/syncthru_mock_server.py
pyernluefter/tests/web_raw/__init__.py
pyernluefter/tests/web_raw/web_state.py
pyernluefter-0.0.1.dist-info/LICENSE
pyernluefter-0.0.1.dist-info/METADATA
pyernluefter-0.0.1.dist-info/WHEEL
pyernluefter-0.0.1.dist-info/top_level.txt
pyernluefter-0.0.1.dist-info/RECORD
