Metadata-Version: 2.1
Name: pyernluefter
Version: 0.0.1
Summary: Automated async web-based communication with the Bayernluefter
Home-page: https://github.com/nielstron/pyernluefter/
Author: nielstron
Author-email: n.muendler@web.de
License: MIT
Keywords: python api iot async bayernluft bayernluefter
Platform: UNKNOWN
Classifier: Development Status :: 3 - Alpha
Classifier: Intended Audience :: Developers
Classifier: Topic :: Software Development :: Object Brokering
Classifier: License :: OSI Approved :: MIT License
Classifier: Programming Language :: Python :: 3.7
Classifier: Programming Language :: Python :: 3.8
Requires-Python: >=3
Requires-Dist: aiohttp
Requires-Dist: parse
